newsstructure/__init__.py
newsstructure/main.py
newsstructure/prompts.py
newsstructure-2025.12.20202005.dist-info/METADATA
newsstructure-2025.12.20202005.dist-info/WHEEL
newsstructure-2025.12.20202005.dist-info/top_level.txt
newsstructure-2025.12.20202005.dist-info/RECORD
