Metadata-Version: 2.4
Name: newsstructure
Version: 2025.12.20202005
Summary: A new package that takes a news headline or short text snippet as input and returns a structured summary of the key event, actors, and context, using an LLM to generate the content and pattern matchin
Author-email: newsstructure <hi@eugene.plus>
License: MIT
Project-URL: Homepage, https://github.com/chigwell/newsstructure
Requires-Python: >=3.9
Requires-Dist: langchain-llm7>=0.0.0
Requires-Dist: llmatch-messages>=0.0.0
Requires-Dist: langchain-core>=0.3.0
